MANIFEST.in
README.rst
setup.cfg
setup.py
c2c.recipe.facts.egg-info/PKG-INFO
c2c.recipe.facts.egg-info/SOURCES.txt
c2c.recipe.facts.egg-info/dependency_links.txt
c2c.recipe.facts.egg-info/entry_points.txt
c2c.recipe.facts.egg-info/not-zip-safe
c2c.recipe.facts.egg-info/requires.txt
c2c.recipe.facts.egg-info/top_level.txt
c2c_recipe_facts/__init__.py