Metadata-Version: 1.1
Name: c2c.recipe.facts
Version: 1.2
Summary: Collect the puppet facter facts
Home-page: http://github.com/sbrunner/c2c.recipe.facts
Author: Stéphane Brunner
Author-email: stephane.brunner@camptocamp.com
License: BSD
Keywords: puppet facts facter
Platform: UNKNOWN
Classifier: Development Status :: 5 - Production/Stable
Classifier: Environment :: Plugins
Classifier: Intended Audience :: Developers
Classifier: License :: OSI Approved :: BSD License
Classifier: Programming Language :: Python
Classifier: Framework :: Buildout :: Recipe
Classifier: Topic :: System :: Installation/Setup
